tensortime/__init__.py
tensortime/time_machine.py
tensortime-0.1.0.dist-info/LICENSE
tensortime-0.1.0.dist-info/METADATA
tensortime-0.1.0.dist-info/WHEEL
tensortime-0.1.0.dist-info/top_level.txt
tensortime-0.1.0.dist-info/zip-safe
tensortime-0.1.0.dist-info/RECORD
