Metadata-Version: 2.1
Name: tensortime
Version: 0.1.0
Summary: Let your experiment have the ability to go back.
Home-page: https://github.com/dovolopor-research/tensortime
Author: Ailln
Author-email: kinggreenhall@gmail.com
License: MIT License
Platform: UNKNOWN
Classifier: Programming Language :: Python :: 3
Classifier: License :: OSI Approved :: MIT License
Classifier: Operating System :: OS Independent
Requires-Python: >=3.6
Requires-Dist: setuptools (>=40.6.3)
